tmt/__init__.py
tmt/__main__.py
tmt/_bootstrap.py
tmt/ansible.py
tmt/base.py
tmt/convert.py
tmt/hardware.py
tmt/identifier.py
tmt/lint.py
tmt/log.py
tmt/options.py
tmt/policy.py
tmt/py.typed
tmt/queue.py
tmt/recipe.py
tmt/result.py
tmt/trying.py
tmt/_compat/__init__.py
tmt/_compat/annotationlib.py
tmt/_compat/pathlib.py
tmt/_compat/pydantic.py
tmt/_compat/typing.py
tmt/_compat/warnings.py
tmt/_compat/importlib/__init__.py
tmt/_compat/importlib/metadata.py
tmt/_compat/importlib/readers.py
tmt/_compat/importlib/resources.py
tmt/_pre_commit/__init__.py
tmt/_pre_commit/__main__.py
tmt/checks/__init__.py
tmt/checks/avc.py
tmt/checks/coredump.py
tmt/checks/dmesg.py
tmt/checks/journal.py
tmt/checks/watchdog.py
tmt/checks/internal/__init__.py
tmt/checks/internal/abort.py
tmt/checks/internal/guest.py
tmt/checks/internal/interrupt.py
tmt/checks/internal/invocation.py
tmt/checks/internal/permission.py
tmt/checks/internal/timeout.py
tmt/cli/__init__.py
tmt/cli/_root.py
tmt/cli/about.py
tmt/cli/init.py
tmt/cli/lint.py
tmt/cli/status.py
tmt/cli/trying.py
tmt/cli/templates/about/hints-ls.rst.j2
tmt/cli/templates/about/plugins-ls.rst.j2
tmt/config/__init__.py
tmt/config/models/__init__.py
tmt/config/models/hardware.py
tmt/config/models/link.py
tmt/config/models/themes.py
tmt/config/themes/default.yaml
tmt/config/themes/plain.yaml
tmt/container/__init__.py
tmt/export/__init__.py
tmt/export/_dict.py
tmt/export/_json.py
tmt/export/nitrate.py
tmt/export/polarion.py
tmt/export/rst.py
tmt/export/template.py
tmt/export/yaml.py
tmt/export/templates/default-story.rst.j2
tmt/frameworks/__init__.py
tmt/frameworks/beakerlib.py
tmt/frameworks/shell.py
tmt/libraries/__init__.py
tmt/libraries/beakerlib.py
tmt/libraries/file.py
tmt/package_managers/__init__.py
tmt/package_managers/apk.py
tmt/package_managers/apt.py
tmt/package_managers/bootc.py
tmt/package_managers/dnf.py
tmt/package_managers/mock.py
tmt/package_managers/rpm_ostree.py
tmt/plugins/__init__.py
tmt/plugins/plan_shapers/__init__.py
tmt-1.65.0.dist-info/METADATA
tmt-1.65.0.dist-info/WHEEL
tmt-1.65.0.dist-info/entry_points.txt
tmt-1.65.0.dist-info/licenses/LICENSE
tmt-1.65.0.dist-info/RECORD
