Metadata-Version: 2.4
Name: tmt
Version: 1.65.0
Summary: Test Management Tool
Project-URL: Homepage, https://github.com/teemtee/tmt
Author-email: Petr Splichal <psplicha@redhat.com>
Maintainer-email: Petr Splichal <psplicha@redhat.com>
License-Expression: MIT
License-File: LICENSE
Keywords: metadata,testing
Classifier: License :: OSI Approved :: MIT License
Classifier: Natural Language :: English
Classifier: Operating System :: POSIX :: Linux
Classifier: Programming Language :: Python :: 3.9
Classifier: Programming Language :: Python :: 3.10
Classifier: Programming Language :: Python :: 3.11
Classifier: Programming Language :: Python :: 3.12
Classifier: Programming Language :: Python :: 3.13
Classifier: Topic :: Software Development :: Testing
Classifier: Topic :: Utilities
Requires-Python: >=3.9
Requires-Dist: click>=8.0.3
Requires-Dist: docutils>=0.16
Requires-Dist: fmf>=1.7.0
Requires-Dist: importlib-metadata>=3.6.0; python_version < '3.10'
Requires-Dist: importlib-resources; python_version < '3.12'
Requires-Dist: jinja2>=2.11.3
Requires-Dist: packaging>=20.9
Requires-Dist: pint>=0.16.1
Requires-Dist: pydantic>=1.10.14
Requires-Dist: pydantic>=2.12.0a1; python_version >= '3.14'
Requires-Dist: pygments>=2.7.4
Requires-Dist: requests>=2.25.1
Requires-Dist: ruamel-yaml>=0.16.6
Requires-Dist: typing-extensions>=4; python_version < '3.13'
Requires-Dist: urllib3<3.0,>=1.26.5
Provides-Extra: all
Requires-Dist: copr>=2.4; extra == 'all'
Requires-Dist: html2text>=2020.1.16; extra == 'all'
Requires-Dist: jira<4,>=3.5.0; extra == 'all'
Requires-Dist: koji>=1.35.0; extra == 'all'
Requires-Dist: lxml>=4.6.5; extra == 'all'
Requires-Dist: markdown>=3.3.4; extra == 'all'
Requires-Dist: mrack>=1.25.0; extra == 'all'
Requires-Dist: nitrate>=1.9.0; extra == 'all'
Requires-Dist: pylero>=0.1.0; extra == 'all'
Requires-Dist: python-bugzilla>=3.2.0; extra == 'all'
Requires-Dist: testcloud>=0.11.7; extra == 'all'
Provides-Extra: ansible
Requires-Dist: ansible-core>=2.14.18; extra == 'ansible'
Provides-Extra: docs
Requires-Dist: docutils>=0.18.1; extra == 'docs'
Requires-Dist: fmf>=1.7.0; extra == 'docs'
Requires-Dist: readthedocs-sphinx-ext; extra == 'docs'
Requires-Dist: renku-sphinx-theme; extra == 'docs'
Requires-Dist: sphinx; extra == 'docs'
Requires-Dist: sphinx-reredirects; extra == 'docs'
Provides-Extra: export-polarion
Requires-Dist: pylero>=0.1.0; extra == 'export-polarion'
Provides-Extra: link-jira
Requires-Dist: jira<4,>=3.5.0; extra == 'link-jira'
Provides-Extra: prepare-artifact
Requires-Dist: copr>=2.4; extra == 'prepare-artifact'
Requires-Dist: koji>=1.35.0; extra == 'prepare-artifact'
Provides-Extra: provision-beaker
Requires-Dist: mrack>=1.25.0; extra == 'provision-beaker'
Provides-Extra: provision-bootc
Requires-Dist: testcloud>=0.11.7; extra == 'provision-bootc'
Provides-Extra: provision-container
Provides-Extra: provision-mock
Provides-Extra: provision-virtual
Requires-Dist: testcloud>=0.11.7; extra == 'provision-virtual'
Provides-Extra: report-junit
Requires-Dist: lxml>=4.6.5; extra == 'report-junit'
Provides-Extra: report-polarion
Requires-Dist: lxml>=4.6.5; extra == 'report-polarion'
Requires-Dist: pylero>=0.1.0; extra == 'report-polarion'
Provides-Extra: test-convert
Requires-Dist: html2text>=2020.1.16; extra == 'test-convert'
Requires-Dist: markdown>=3.3.4; extra == 'test-convert'
Requires-Dist: nitrate>=1.9.0; extra == 'test-convert'
Requires-Dist: python-bugzilla>=3.2.0; extra == 'test-convert'
